{
  "titel": "DICOM JSON Model",
  "externalDocs": {
    "description": "DICOM PS3.18 F",
    "url": "https://dicom.nema.org/medical/dicom/current/output/html/part18.html#chapter_F"
  },
  "type": "array",
  "items": {
    "type": "object",
    "properties": {
      "{ggggeeee}": {
        "required": [
          "vr"
        ],
        "properties": {
          "vr" : {
            "type": "string",
            "enum": [
              "AE",
              "AS",
              "AT",
              "CS",
              "DA",
              "DS",
              "DT",
              "FD",
              "FL",
              "IS",
              "LO",
              "LT",
              "OB",
              "OD",
              "OF",
              "OL",
              "OV",
              "OW",
              "PN",
              "SH",
              "SL",
              "SQ",
              "SS",
              "ST",
              "SV",
              "TM",
              "UC",
              "UI",
              "UL",
              "UN",
              "UR",
              "US",
              "UT",
              "UV"
            ]
          },
          "Value": {
            "type": "array",
            "items": {
              "type": "string"
            }
          }
        }
      }
    }
  }
}
